firebase_orm/__init__.py
firebase_orm/exceptions.py
firebase_orm/models/__init__.py
firebase_orm/models/base.py
firebase_orm/models/manager.py
firebase_orm/models/fields/__init__.py
django_firebase_orm-0.6.1.dist-info/LICENSE
django_firebase_orm-0.6.1.dist-info/METADATA
django_firebase_orm-0.6.1.dist-info/WHEEL
django_firebase_orm-0.6.1.dist-info/top_level.txt
django_firebase_orm-0.6.1.dist-info/RECORD
