Metadata-Version: 2.1
Name: django-firebase-orm
Version: 0.6.1
Summary: NoSQL object model database for django ORM integration
Home-page: https://github.com/TralahM/firebase_orm
Author: Tralah M Brian
Author-email: musyoki.brian@tralahtek.com
License: MIT
Platform: UNKNOWN
